modelzoo/__init__.py
modelzoo/admin.py
modelzoo/clipper.py
modelzoo/exceptions.py
modelzoo/sugar.py
modelzoo/utils.py
modelzoo/protos/__init__.py
modelzoo/protos/services_pb2.py
modelzoo/protos/services_pb2_grpc.py
modelzoo/test/__init__.py
modelzoo/test/test_clipper.py
modelzoo/test/test_modelzoo.py
modelzoo/test/test_sugar.py
modelzoo-0.3.3.dist-info/METADATA
modelzoo-0.3.3.dist-info/WHEEL
modelzoo-0.3.3.dist-info/top_level.txt
modelzoo-0.3.3.dist-info/RECORD
