Metadata-Version: 2.1
Name: modelzoo
Version: 0.3.3
Summary: Python package for querying ModelZoo.Live
Home-page: https://github.com/harbor-ml/modelzoo
Author: Rehan Durrani
Author-email: rdurrani@berkeley.edu
License: UNKNOWN
Platform: UNKNOWN
Classifier: Development Status :: 1 - Planning
Classifier: License :: OSI Approved :: Apache Software License
Classifier: Programming Language :: Python :: 3 :: Only
Requires-Python: >=3.6
